{
  "record_id": "2022-grille-8",
  "grid_type": "grid-7",
  "season": "2021-2022",
  "date": "11/01/2022",
  "date_full": "Mardi 11 Janvier 2022 à 20h40",
  "competition": "Autre",
  "pactole_eur": null,
  "enjeux_eur": 123494.0,
  "rang1_eur": 55.0,
  "rang2_eur": 7.3,
  "nb_entries": 1483,
  "total_combinations": 11864,
  "matches": [
    {
      "num": 1,
      "time": "14h00",
      "home": "Tunisie",
      "away": "Mali",
      "result": "2",
      "score": "0-1",
      "cote_1": 2.7,
      "cote_n": 2.7,
      "cote_2": 3.2,
      "cyborg_pct_1": 58.0,
      "cyborg_pct_n": 15.0,
      "cyborg_pct_2": 27.0,
      "cyborg_pct_u": 38.0,
      "cyborg_pct_o": 62.0,
      "cyborg_prono": "1",
      "cyborg_prono_uo": "O",
      "cyborg_fav": "1",
      "cyborg_fav_uo": "O",
      "bettor_pct_1": 58.3,
      "bettor_pct_n": 26.3,
      "bettor_pct_2": 15.5
    },
    {
      "num": 2,
      "time": "17h00",
      "home": "Mauritanie",
      "away": "Gambie",
      "result": "2",
      "score": "0-1",
      "cote_1": 3.2,
      "cote_n": 2.8,
      "cote_2": 2.7,
      "cyborg_pct_1": 37.0,
      "cyborg_pct_n": 37.0,
      "cyborg_pct_2": 26.0,
      "cyborg_pct_u": 81.0,
      "cyborg_pct_o": 19.0,
      "cyborg_prono": "1N",
      "cyborg_prono_uo": "U",
      "cyborg_fav": "1",
      "cyborg_fav_uo": "U",
      "bettor_pct_1": 34.1,
      "bettor_pct_n": 35.9,
      "bettor_pct_2": 30.0
    },
    {
      "num": 3,
      "time": "20h45",
      "home": "Southampton",
      "away": "Brentford",
      "result": "1",
      "score": "4-1",
      "cote_1": 2.15,
      "cote_n": 3.3,
      "cote_2": 3.65,
      "cyborg_pct_1": 22.0,
      "cyborg_pct_n": 51.0,
      "cyborg_pct_2": 27.0,
      "cyborg_pct_u": 65.0,
      "cyborg_pct_o": 35.0,
      "cyborg_prono": "N",
      "cyborg_prono_uo": "U",
      "cyborg_fav": "N",
      "cyborg_fav_uo": "U",
      "bettor_pct_1": 66.3,
      "bettor_pct_n": 22.1,
      "bettor_pct_2": 11.5
    },
    {
      "num": 4,
      "time": "21h45",
      "home": "Leca FC",
      "away": "Sportng Lisbon",
      "result": "2",
      "score": "0-4",
      "cote_1": 20.0,
      "cote_n": 9.9,
      "cote_2": 1.09,
      "cyborg_pct_1": null,
      "cyborg_pct_n": null,
      "cyborg_pct_2": null,
      "cyborg_pct_u": null,
      "cyborg_pct_o": null,
      "cyborg_prono": null,
      "cyborg_prono_uo": null,
      "cyborg_fav": null,
      "cyborg_fav_uo": null,
      "bettor_pct_1": 3.71,
      "bettor_pct_n": 7.17,
      "bettor_pct_2": 89.1
    },
    {
      "num": 5,
      "time": "21h00",
      "home": "Reading",
      "away": "Fulham",
      "result": "2",
      "score": "0-7",
      "cote_1": 6.5,
      "cote_n": 4.6,
      "cote_2": 1.4,
      "cyborg_pct_1": 8.0,
      "cyborg_pct_n": 24.0,
      "cyborg_pct_2": 69.0,
      "cyborg_pct_u": 63.0,
      "cyborg_pct_o": 38.0,
      "cyborg_prono": "2",
      "cyborg_prono_uo": "U",
      "cyborg_fav": "2",
      "cyborg_fav_uo": "U",
      "bettor_pct_1": 33.8,
      "bettor_pct_n": 28.0,
      "bettor_pct_2": 38.1
    },
    {
      "num": 6,
      "time": "20h45",
      "home": "Cagliari",
      "away": "Bologne",
      "result": "1",
      "score": "2-1",
      "cote_1": 3.0,
      "cote_n": 3.3,
      "cote_2": 2.5,
      "cyborg_pct_1": 23.0,
      "cyborg_pct_n": 43.0,
      "cyborg_pct_2": 34.0,
      "cyborg_pct_u": 62.0,
      "cyborg_pct_o": 38.0,
      "cyborg_prono": "N",
      "cyborg_prono_uo": "U",
      "cyborg_fav": "N",
      "cyborg_fav_uo": "U",
      "bettor_pct_1": 40.8,
      "bettor_pct_n": 33.3,
      "bettor_pct_2": 25.9
    },
    {
      "num": 7,
      "time": "17h30",
      "home": "Atalanta",
      "away": "Venezia FC",
      "result": "1",
      "score": "2-0",
      "cote_1": 1.25,
      "cote_n": 6.6,
      "cote_2": 12.0,
      "cyborg_pct_1": null,
      "cyborg_pct_n": null,
      "cyborg_pct_2": null,
      "cyborg_pct_u": null,
      "cyborg_pct_o": null,
      "cyborg_prono": null,
      "cyborg_prono_uo": null,
      "cyborg_fav": null,
      "cyborg_fav_uo": null,
      "bettor_pct_1": 91.4,
      "bettor_pct_n": 6.38,
      "bettor_pct_2": 2.19
    }
  ],
  "ranks": [
    {
      "rank": 7,
      "nb_winners": 1007,
      "payout_eur": 55.0
    },
    {
      "rank": 6,
      "nb_winners": 9330,
      "payout_eur": 7.3
    }
  ],
  "stats": {
    "nb_1": 3,
    "nb_n": 0,
    "nb_2": 4,
    "cons_1": 2,
    "cons_n": 0,
    "cons_2": 2,
    "diagonales": 0,
    "symetries": 0,
    "alternances": 3,
    "paires": 4,
    "tierces": 4,
    "quartes": 4
  }
}