{
  "record_id": "2019-grille-137",
  "grid_type": "grid-7",
  "season": "2018-2019",
  "date": "17/05/2019",
  "date_full": "Vendredi 17 Mai 2019 à 20h25",
  "competition": "Autre",
  "pactole_eur": null,
  "enjeux_eur": 188918.0,
  "rang1_eur": 45.0,
  "rang2_eur": 5.7,
  "nb_entries": 1952,
  "total_combinations": 15616,
  "matches": [
    {
      "num": 1,
      "time": "20h30",
      "home": "Mouscron",
      "away": "KV Beveren",
      "result": "2",
      "score": "2-4",
      "cote_1": 1.38,
      "cote_n": 4.9,
      "cote_2": 5.4,
      "cyborg_pct_1": 46.0,
      "cyborg_pct_n": 29.0,
      "cyborg_pct_2": 26.0,
      "cyborg_pct_u": 49.0,
      "cyborg_pct_o": 51.0,
      "cyborg_prono": null,
      "cyborg_prono_uo": null,
      "cyborg_fav": null,
      "cyborg_fav_uo": null,
      "bettor_pct_1": 58.3,
      "bettor_pct_n": 22.7,
      "bettor_pct_2": 19.0
    },
    {
      "num": 2,
      "time": "20h30",
      "home": "Zulte Waregem",
      "away": "Saint-Gilloise",
      "result": "1",
      "score": "2-1",
      "cote_1": 2.6,
      "cote_n": 3.85,
      "cote_2": 2.15,
      "cyborg_pct_1": 7.0,
      "cyborg_pct_n": 23.0,
      "cyborg_pct_2": 70.0,
      "cyborg_pct_u": 23.0,
      "cyborg_pct_o": 77.0,
      "cyborg_prono": "2",
      "cyborg_prono_uo": "O",
      "cyborg_fav": "2",
      "cyborg_fav_uo": "O",
      "bettor_pct_1": 56.3,
      "bettor_pct_n": 22.3,
      "bettor_pct_2": 21.3
    },
    {
      "num": 3,
      "time": "20h30",
      "home": "Courtrai",
      "away": "Cercle Bruges",
      "result": "1",
      "score": "4-0",
      "cote_1": 1.45,
      "cote_n": 4.4,
      "cote_2": 5.0,
      "cyborg_pct_1": 77.0,
      "cyborg_pct_n": 7.0,
      "cyborg_pct_2": 16.0,
      "cyborg_pct_u": 33.0,
      "cyborg_pct_o": 67.0,
      "cyborg_prono": "1",
      "cyborg_prono_uo": "O",
      "cyborg_fav": "1",
      "cyborg_fav_uo": "O",
      "bettor_pct_1": 52.7,
      "bettor_pct_n": 22.7,
      "bettor_pct_2": 24.6
    },
    {
      "num": 4,
      "time": "20h45",
      "home": "UCD",
      "away": "Shamrock",
      "result": "2",
      "score": "0-1",
      "cote_1": 13.0,
      "cote_n": 4.9,
      "cote_2": 1.25,
      "cyborg_pct_1": 17.0,
      "cyborg_pct_n": 10.0,
      "cyborg_pct_2": 73.0,
      "cyborg_pct_u": 48.0,
      "cyborg_pct_o": 52.0,
      "cyborg_prono": "2",
      "cyborg_prono_uo": null,
      "cyborg_fav": "2",
      "cyborg_fav_uo": null,
      "bettor_pct_1": 20.6,
      "bettor_pct_n": 23.4,
      "bettor_pct_2": 56.0
    },
    {
      "num": 5,
      "time": "20h45",
      "home": "Cork City FC",
      "away": "Dundalk",
      "result": "2",
      "score": "0-2",
      "cote_1": 4.7,
      "cote_n": 3.25,
      "cote_2": 1.61,
      "cyborg_pct_1": 13.0,
      "cyborg_pct_n": 48.0,
      "cyborg_pct_2": 39.0,
      "cyborg_pct_u": 75.0,
      "cyborg_pct_o": 25.0,
      "cyborg_prono": "N",
      "cyborg_prono_uo": "U",
      "cyborg_fav": "N",
      "cyborg_fav_uo": "U",
      "bettor_pct_1": 37.4,
      "bettor_pct_n": 24.0,
      "bettor_pct_2": 38.5
    },
    {
      "num": 6,
      "time": "21h00",
      "home": "Saragosse",
      "away": "Gijon",
      "result": "1",
      "score": "4-2",
      "cote_1": 1.81,
      "cote_n": 3.2,
      "cote_2": 3.6,
      "cyborg_pct_1": 14.0,
      "cyborg_pct_n": 43.0,
      "cyborg_pct_2": 43.0,
      "cyborg_pct_u": 68.0,
      "cyborg_pct_o": 32.0,
      "cyborg_prono": "N2",
      "cyborg_prono_uo": "U",
      "cyborg_fav": "N",
      "cyborg_fav_uo": "U",
      "bettor_pct_1": 49.4,
      "bettor_pct_n": 31.7,
      "bettor_pct_2": 18.9
    },
    {
      "num": 7,
      "time": "20h45",
      "home": "Paris FC",
      "away": "GFC Ajaccio",
      "result": "1",
      "score": "1-0",
      "cote_1": 1.9,
      "cote_n": 3.45,
      "cote_2": 5.0,
      "cyborg_pct_1": 35.0,
      "cyborg_pct_n": 50.0,
      "cyborg_pct_2": 16.0,
      "cyborg_pct_u": 64.0,
      "cyborg_pct_o": 36.0,
      "cyborg_prono": "N",
      "cyborg_prono_uo": "U",
      "cyborg_fav": "N",
      "cyborg_fav_uo": "U",
      "bettor_pct_1": 71.2,
      "bettor_pct_n": 20.7,
      "bettor_pct_2": 8.12
    }
  ],
  "ranks": [
    {
      "rank": 7,
      "nb_winners": 1894,
      "payout_eur": 45.0
    },
    {
      "rank": 6,
      "nb_winners": 18191,
      "payout_eur": 5.7
    }
  ],
  "stats": {
    "nb_1": 4,
    "nb_n": 0,
    "nb_2": 3,
    "cons_1": 2,
    "cons_n": 0,
    "cons_2": 2,
    "diagonales": 0,
    "symetries": 1,
    "alternances": 3,
    "paires": 4,
    "tierces": 4,
    "quartes": 4
  }
}