{
  "record_id": "2020-grille-27",
  "grid_type": "grid-8",
  "season": "2020-2021",
  "date": "05/12/2020",
  "date_full": "Samedi 5 Décembre 2020 à 18h55",
  "competition": "Ligue 2",
  "pactole_eur": 150000.0,
  "enjeux_eur": 464543.0,
  "rang1_eur": 553.0,
  "rang2_eur": 50.0,
  "nb_entries": 1943,
  "total_combinations": 31088,
  "matches": [
    {
      "num": 1,
      "time": "19h00",
      "home": "Auxerre",
      "away": "Niort",
      "result": "1",
      "score": "6-0",
      "cote_1": 1.94,
      "cote_n": 3.35,
      "cote_2": 3.8,
      "cyborg_pct_1": 41.0,
      "cyborg_pct_n": 17.0,
      "cyborg_pct_2": 42.0,
      "cyborg_pct_u": 30.0,
      "cyborg_pct_o": 70.0,
      "cyborg_prono": null,
      "cyborg_prono_uo": "O",
      "cyborg_fav": null,
      "cyborg_fav_uo": "O",
      "bettor_pct_1": 68.8,
      "bettor_pct_n": 21.1,
      "bettor_pct_2": 10.0
    },
    {
      "num": 2,
      "time": "19h00",
      "home": "Toulouse",
      "away": "Guingamp",
      "result": "N",
      "score": "2-2",
      "cote_1": 2.5,
      "cote_n": 3.05,
      "cote_2": 2.85,
      "cyborg_pct_1": 35.0,
      "cyborg_pct_n": 40.0,
      "cyborg_pct_2": 25.0,
      "cyborg_pct_u": 45.0,
      "cyborg_pct_o": 55.0,
      "cyborg_prono": "N",
      "cyborg_prono_uo": null,
      "cyborg_fav": "N",
      "cyborg_fav_uo": null,
      "bettor_pct_1": 65.5,
      "bettor_pct_n": 22.0,
      "bettor_pct_2": 12.5
    },
    {
      "num": 3,
      "time": "19h00",
      "home": "Clermont",
      "away": "Pau",
      "result": "1",
      "score": "3-0",
      "cote_1": 1.7,
      "cote_n": 3.4,
      "cote_2": 5.1,
      "cyborg_pct_1": 43.0,
      "cyborg_pct_n": 37.0,
      "cyborg_pct_2": 21.0,
      "cyborg_pct_u": 67.0,
      "cyborg_pct_o": 33.0,
      "cyborg_prono": "1N",
      "cyborg_prono_uo": "U",
      "cyborg_fav": "1",
      "cyborg_fav_uo": "U",
      "bettor_pct_1": 69.0,
      "bettor_pct_n": 19.0,
      "bettor_pct_2": 12.0
    },
    {
      "num": 4,
      "time": "19h00",
      "home": "Rodez",
      "away": "Amiens",
      "result": "2",
      "score": "1-2",
      "cote_1": 2.65,
      "cote_n": 2.75,
      "cote_2": 2.85,
      "cyborg_pct_1": 38.0,
      "cyborg_pct_n": 28.0,
      "cyborg_pct_2": 34.0,
      "cyborg_pct_u": 67.0,
      "cyborg_pct_o": 33.0,
      "cyborg_prono": null,
      "cyborg_prono_uo": "U",
      "cyborg_fav": null,
      "cyborg_fav_uo": "U",
      "bettor_pct_1": 25.3,
      "bettor_pct_n": 34.6,
      "bettor_pct_2": 40.1
    },
    {
      "num": 5,
      "time": "19h00",
      "home": "Chambly",
      "away": "Valenciennes",
      "result": "2",
      "score": "1-2",
      "cote_1": 2.85,
      "cote_n": 2.9,
      "cote_2": 2.5,
      "cyborg_pct_1": 32.0,
      "cyborg_pct_n": 28.0,
      "cyborg_pct_2": 40.0,
      "cyborg_pct_u": 68.0,
      "cyborg_pct_o": 32.0,
      "cyborg_prono": null,
      "cyborg_prono_uo": "U",
      "cyborg_fav": null,
      "cyborg_fav_uo": "U",
      "bettor_pct_1": 21.9,
      "bettor_pct_n": 32.8,
      "bettor_pct_2": 45.3
    },
    {
      "num": 6,
      "time": "19h00",
      "home": "Sochaux",
      "away": "Nancy",
      "result": "N",
      "score": "1-1",
      "cote_1": 2.3,
      "cote_n": 2.8,
      "cote_2": 3.4,
      "cyborg_pct_1": 66.0,
      "cyborg_pct_n": 16.0,
      "cyborg_pct_2": 18.0,
      "cyborg_pct_u": 57.0,
      "cyborg_pct_o": 43.0,
      "cyborg_prono": "1",
      "cyborg_prono_uo": "U",
      "cyborg_fav": "1",
      "cyborg_fav_uo": "U",
      "bettor_pct_1": 65.9,
      "bettor_pct_n": 23.4,
      "bettor_pct_2": 10.8
    },
    {
      "num": 7,
      "time": "19h00",
      "home": "Dunkerque",
      "away": "Châteauroux",
      "result": "1",
      "score": "2-0",
      "cote_1": 2.4,
      "cote_n": 2.85,
      "cote_2": 3.1,
      "cyborg_pct_1": 33.0,
      "cyborg_pct_n": 37.0,
      "cyborg_pct_2": 30.0,
      "cyborg_pct_u": 68.0,
      "cyborg_pct_o": 32.0,
      "cyborg_prono": "1N",
      "cyborg_prono_uo": "U",
      "cyborg_fav": "1",
      "cyborg_fav_uo": "U",
      "bettor_pct_1": 53.8,
      "bettor_pct_n": 28.1,
      "bettor_pct_2": 18.1
    },
    {
      "num": 8,
      "time": "19h00",
      "home": "Caen",
      "away": "Grenoble",
      "result": "N",
      "score": "1-1",
      "cote_1": 2.55,
      "cote_n": 2.9,
      "cote_2": 2.85,
      "cyborg_pct_1": 43.0,
      "cyborg_pct_n": 25.0,
      "cyborg_pct_2": 32.0,
      "cyborg_pct_u": 67.0,
      "cyborg_pct_o": 33.0,
      "cyborg_prono": null,
      "cyborg_prono_uo": "U",
      "cyborg_fav": null,
      "cyborg_fav_uo": "U",
      "bettor_pct_1": 51.3,
      "bettor_pct_n": 28.1,
      "bettor_pct_2": 20.6
    }
  ],
  "ranks": [
    {
      "rank": 8,
      "nb_winners": 381,
      "payout_eur": 553.0
    },
    {
      "rank": 7,
      "nb_winners": 5077,
      "payout_eur": 50.0
    }
  ],
  "stats": {
    "nb_1": 3,
    "nb_n": 3,
    "nb_2": 2,
    "cons_1": 1,
    "cons_n": 1,
    "cons_2": 2,
    "diagonales": 1,
    "symetries": 1,
    "alternances": 6,
    "paires": 5,
    "tierces": 6,
    "quartes": 5
  }
}