{
  "record_id": "2023-grille-81",
  "grid_type": "grid-12",
  "season": "2023-2024",
  "date": "09/12/2023",
  "date_full": "Samedi 9 Décembre 2023 à 16h55",
  "competition": "Autre",
  "pactole_eur": 200000.0,
  "enjeux_eur": 3.8,
  "rang1_eur": 109.1,
  "rang2_eur": 14.5,
  "nb_entries": 1440,
  "total_combinations": 103680,
  "matches": [
    {
      "num": 1,
      "time": "21h00",
      "home": "Paris SG",
      "away": "Nantes",
      "result": "1",
      "score": "2-1",
      "cote_1": 1.22,
      "cote_n": 6.75,
      "cote_2": 11.5,
      "cyborg_pct_1": 74.0,
      "cyborg_pct_n": 10.0,
      "cyborg_pct_2": 16.0,
      "cyborg_pct_u": 25.0,
      "cyborg_pct_o": 75.0,
      "cyborg_prono": "1",
      "cyborg_prono_uo": "O",
      "cyborg_fav": "1",
      "cyborg_fav_uo": "O",
      "bettor_pct_1": 89.4,
      "bettor_pct_n": 6.93,
      "bettor_pct_2": 3.68
    },
    {
      "num": 2,
      "time": "17h00",
      "home": "Rennes",
      "away": "Monaco",
      "result": "2",
      "score": "1-2",
      "cote_1": 2.75,
      "cote_n": 3.7,
      "cote_2": 2.4,
      "cyborg_pct_1": 27.0,
      "cyborg_pct_n": 40.0,
      "cyborg_pct_2": 33.0,
      "cyborg_pct_u": 45.0,
      "cyborg_pct_o": 55.0,
      "cyborg_prono": "N",
      "cyborg_prono_uo": null,
      "cyborg_fav": "N",
      "cyborg_fav_uo": null,
      "bettor_pct_1": 31.1,
      "bettor_pct_n": 33.6,
      "bettor_pct_2": 35.2
    },
    {
      "num": 3,
      "time": "18h30",
      "home": "Aston Villa",
      "away": "Arsenal",
      "result": "1",
      "score": "1-0",
      "cote_1": 3.55,
      "cote_n": 3.65,
      "cote_2": 2.0,
      "cyborg_pct_1": 45.0,
      "cyborg_pct_n": 15.0,
      "cyborg_pct_2": 40.0,
      "cyborg_pct_u": 28.0,
      "cyborg_pct_o": 72.0,
      "cyborg_prono": null,
      "cyborg_prono_uo": "O",
      "cyborg_fav": null,
      "cyborg_fav_uo": "O",
      "bettor_pct_1": 23.8,
      "bettor_pct_n": 26.6,
      "bettor_pct_2": 49.6
    },
    {
      "num": 4,
      "time": "18h30",
      "home": "Dortmund",
      "away": "RB Leipzig",
      "result": "2",
      "score": "2-3",
      "cote_1": 2.6,
      "cote_n": 3.85,
      "cote_2": 2.4,
      "cyborg_pct_1": 46.0,
      "cyborg_pct_n": 16.0,
      "cyborg_pct_2": 38.0,
      "cyborg_pct_u": 29.0,
      "cyborg_pct_o": 71.0,
      "cyborg_prono": null,
      "cyborg_prono_uo": "O",
      "cyborg_fav": null,
      "cyborg_fav_uo": "O",
      "bettor_pct_1": 48.2,
      "bettor_pct_n": 29.1,
      "bettor_pct_2": 22.7
    },
    {
      "num": 5,
      "time": "21h30",
      "home": "FC Porto",
      "away": "Casa Pia",
      "result": "1",
      "score": "3-1",
      "cote_1": 1.19,
      "cote_n": 6.25,
      "cote_2": 12.0,
      "cyborg_pct_1": 35.0,
      "cyborg_pct_n": 32.0,
      "cyborg_pct_2": 33.0,
      "cyborg_pct_u": 66.0,
      "cyborg_pct_o": 34.0,
      "cyborg_prono": null,
      "cyborg_prono_uo": "U",
      "cyborg_fav": null,
      "cyborg_fav_uo": "U",
      "bettor_pct_1": 94.9,
      "bettor_pct_n": 3.53,
      "bettor_pct_2": 1.6
    },
    {
      "num": 6,
      "time": "19h00",
      "home": "Guimaraes",
      "away": "Sporting",
      "result": "1",
      "score": "3-2",
      "cote_1": 4.6,
      "cote_n": 3.9,
      "cote_2": 1.64,
      "cyborg_pct_1": 32.0,
      "cyborg_pct_n": 19.0,
      "cyborg_pct_2": 49.0,
      "cyborg_pct_u": 28.0,
      "cyborg_pct_o": 72.0,
      "cyborg_prono": null,
      "cyborg_prono_uo": "O",
      "cyborg_fav": null,
      "cyborg_fav_uo": "O",
      "bettor_pct_1": 13.8,
      "bettor_pct_n": 23.9,
      "bettor_pct_2": 62.3
    },
    {
      "num": 7,
      "time": "18h45",
      "home": "Ajax",
      "away": "Spar.Rotterdam",
      "result": "1",
      "score": "2-1",
      "cote_1": 1.31,
      "cote_n": 5.1,
      "cote_2": 6.75,
      "cyborg_pct_1": 45.0,
      "cyborg_pct_n": 19.0,
      "cyborg_pct_2": 36.0,
      "cyborg_pct_u": 23.0,
      "cyborg_pct_o": 77.0,
      "cyborg_prono": null,
      "cyborg_prono_uo": "O",
      "cyborg_fav": null,
      "cyborg_fav_uo": "O",
      "bettor_pct_1": 80.0,
      "bettor_pct_n": 12.3,
      "bettor_pct_2": 7.71
    },
    {
      "num": 8,
      "time": "17h00",
      "home": "Besiktas",
      "away": "Fenerbahce",
      "result": "2",
      "score": "1-3",
      "cote_1": 3.72,
      "cote_n": 3.55,
      "cote_2": 1.82,
      "cyborg_pct_1": 30.0,
      "cyborg_pct_n": 31.0,
      "cyborg_pct_2": 39.0,
      "cyborg_pct_u": 32.0,
      "cyborg_pct_o": 68.0,
      "cyborg_prono": null,
      "cyborg_prono_uo": "O",
      "cyborg_fav": null,
      "cyborg_fav_uo": "O",
      "bettor_pct_1": 34.8,
      "bettor_pct_n": 33.4,
      "bettor_pct_2": 31.7
    },
    {
      "num": 9,
      "time": "21h00",
      "home": "Majorque",
      "away": "FC Séville",
      "result": "1",
      "score": "1-0",
      "cote_1": 2.55,
      "cote_n": 2.95,
      "cote_2": 2.95,
      "cyborg_pct_1": 30.0,
      "cyborg_pct_n": 49.0,
      "cyborg_pct_2": 21.0,
      "cyborg_pct_u": 83.0,
      "cyborg_pct_o": 17.0,
      "cyborg_prono": "N",
      "cyborg_prono_uo": "U",
      "cyborg_fav": "N",
      "cyborg_fav_uo": "U",
      "bettor_pct_1": 21.3,
      "bettor_pct_n": 35.2,
      "bettor_pct_2": 43.5
    },
    {
      "num": 10,
      "time": "18h30",
      "home": "Villarreal",
      "away": "Real Sociedad",
      "result": "2",
      "score": "0-3",
      "cote_1": 3.4,
      "cote_n": 3.42,
      "cote_2": 2.1,
      "cyborg_pct_1": 19.0,
      "cyborg_pct_n": 31.0,
      "cyborg_pct_2": 50.0,
      "cyborg_pct_u": 42.0,
      "cyborg_pct_o": 58.0,
      "cyborg_prono": null,
      "cyborg_prono_uo": null,
      "cyborg_fav": null,
      "cyborg_fav_uo": null,
      "bettor_pct_1": 32.4,
      "bettor_pct_n": 34.2,
      "bettor_pct_2": 33.5
    },
    {
      "num": 11,
      "time": "20h45",
      "home": "Inter Milan",
      "away": "Udinese",
      "result": "1",
      "score": "4-0",
      "cote_1": 1.22,
      "cote_n": 6.5,
      "cote_2": 12.0,
      "cyborg_pct_1": 63.0,
      "cyborg_pct_n": 26.0,
      "cyborg_pct_2": 12.0,
      "cyborg_pct_u": 36.0,
      "cyborg_pct_o": 65.0,
      "cyborg_prono": "1",
      "cyborg_prono_uo": "O",
      "cyborg_fav": "1",
      "cyborg_fav_uo": "O",
      "bettor_pct_1": 91.6,
      "bettor_pct_n": 5.34,
      "bettor_pct_2": 3.02
    },
    {
      "num": 12,
      "time": "18h00",
      "home": "Atalanta",
      "away": "Milan AC",
      "result": "1",
      "score": "3-2",
      "cote_1": 2.55,
      "cote_n": 3.2,
      "cote_2": 2.85,
      "cyborg_pct_1": 20.0,
      "cyborg_pct_n": 38.0,
      "cyborg_pct_2": 42.0,
      "cyborg_pct_u": 51.0,
      "cyborg_pct_o": 49.0,
      "cyborg_prono": null,
      "cyborg_prono_uo": null,
      "cyborg_fav": null,
      "cyborg_fav_uo": null,
      "bettor_pct_1": 24.8,
      "bettor_pct_n": 35.4,
      "bettor_pct_2": 39.8
    }
  ],
  "ranks": [
    {
      "rank": 12,
      "nb_winners": 46,
      "payout_eur": 4348.0
    },
    {
      "rank": 11,
      "nb_winners": 776,
      "payout_eur": 109.1
    },
    {
      "rank": 10,
      "nb_winners": 5814,
      "payout_eur": 14.5
    },
    {
      "rank": 9,
      "nb_winners": 21781,
      "payout_eur": 3.8
    }
  ],
  "stats": {
    "nb_1": 8,
    "nb_n": 0,
    "nb_2": 4,
    "cons_1": 3,
    "cons_n": 0,
    "cons_2": 1,
    "diagonales": 0,
    "symetries": 2,
    "alternances": 8,
    "paires": 3,
    "tierces": 5,
    "quartes": 6
  }
}