{
  "record_id": "2016-grille-246",
  "grid_type": "grid-7",
  "season": "2016-2017",
  "date": "06/10/2016",
  "date_full": "Jeudi 6 Octobre 2016 à 20h40",
  "competition": "International",
  "pactole_eur": null,
  "enjeux_eur": 159351.0,
  "rang1_eur": 214.0,
  "rang2_eur": 18.6,
  "nb_entries": 2621,
  "total_combinations": 20968,
  "matches": [
    {
      "num": 1,
      "time": "01h00",
      "home": "Uruguay",
      "away": "Venezuela",
      "result": "1",
      "score": "3-0",
      "cote_1": 1.2,
      "cote_n": 5.6,
      "cote_2": 12.0,
      "cyborg_pct_1": 78.0,
      "cyborg_pct_n": 14.0,
      "cyborg_pct_2": 8.0,
      "cyborg_pct_u": 48.0,
      "cyborg_pct_o": 52.0,
      "cyborg_prono": "1",
      "cyborg_prono_uo": null,
      "cyborg_fav": "1",
      "cyborg_fav_uo": null,
      "bettor_pct_1": 86.1,
      "bettor_pct_n": 9.76,
      "bettor_pct_2": 4.14
    },
    {
      "num": 2,
      "time": "01h30",
      "home": "Paraguay",
      "away": "Colombie",
      "result": "2",
      "score": "0-1",
      "cote_1": 2.75,
      "cote_n": 3.15,
      "cote_2": 2.72,
      "cyborg_pct_1": 42.0,
      "cyborg_pct_n": 35.0,
      "cyborg_pct_2": 23.0,
      "cyborg_pct_u": 48.0,
      "cyborg_pct_o": 52.0,
      "cyborg_prono": "1N",
      "cyborg_prono_uo": null,
      "cyborg_fav": "1",
      "cyborg_fav_uo": null,
      "bettor_pct_1": 27.2,
      "bettor_pct_n": 35.0,
      "bettor_pct_2": 37.8
    },
    {
      "num": 3,
      "time": "23h00",
      "home": "Equateur",
      "away": "Chili",
      "result": "1",
      "score": "3-0",
      "cote_1": 1.95,
      "cote_n": 3.5,
      "cote_2": 3.8,
      "cyborg_pct_1": 39.0,
      "cyborg_pct_n": 22.0,
      "cyborg_pct_2": 38.0,
      "cyborg_pct_u": 31.0,
      "cyborg_pct_o": 69.0,
      "cyborg_prono": null,
      "cyborg_prono_uo": "O",
      "cyborg_fav": null,
      "cyborg_fav_uo": "O",
      "bettor_pct_1": 27.6,
      "bettor_pct_n": 31.9,
      "bettor_pct_2": 40.5
    },
    {
      "num": 4,
      "time": "02h45",
      "home": "Brésil",
      "away": "Bolivie",
      "result": "1",
      "score": "5-0",
      "cote_1": 1.07,
      "cote_n": 11.0,
      "cote_2": 32.0,
      "cyborg_pct_1": 75.0,
      "cyborg_pct_n": 16.0,
      "cyborg_pct_2": 9.0,
      "cyborg_pct_u": 31.0,
      "cyborg_pct_o": 69.0,
      "cyborg_prono": "1",
      "cyborg_prono_uo": "O",
      "cyborg_fav": "1",
      "cyborg_fav_uo": "O",
      "bettor_pct_1": 94.0,
      "bettor_pct_n": 4.74,
      "bettor_pct_2": 1.23
    },
    {
      "num": 5,
      "time": "04h15",
      "home": "Pérou",
      "away": "Argentine",
      "result": "N",
      "score": "2-2",
      "cote_1": 5.0,
      "cote_n": 3.45,
      "cote_2": 1.67,
      "cyborg_pct_1": 20.0,
      "cyborg_pct_n": 30.0,
      "cyborg_pct_2": 49.0,
      "cyborg_pct_u": 45.0,
      "cyborg_pct_o": 55.0,
      "cyborg_prono": "2",
      "cyborg_prono_uo": null,
      "cyborg_fav": "2",
      "cyborg_fav_uo": null,
      "bettor_pct_1": 6.27,
      "bettor_pct_n": 20.5,
      "bettor_pct_2": 73.3
    },
    {
      "num": 6,
      "time": "20h45",
      "home": "Turquie",
      "away": "Ukraine",
      "result": "N",
      "score": "2-2",
      "cote_1": 2.3,
      "cote_n": 3.2,
      "cote_2": 3.5,
      "cyborg_pct_1": 38.0,
      "cyborg_pct_n": 29.0,
      "cyborg_pct_2": 32.0,
      "cyborg_pct_u": 50.0,
      "cyborg_pct_o": 50.0,
      "cyborg_prono": null,
      "cyborg_prono_uo": null,
      "cyborg_fav": null,
      "cyborg_fav_uo": null,
      "bettor_pct_1": 58.6,
      "bettor_pct_n": 29.6,
      "bettor_pct_2": 11.8
    },
    {
      "num": 7,
      "time": "20h45",
      "home": "Italie",
      "away": "Espagne",
      "result": "N",
      "score": "1-1",
      "cote_1": 3.3,
      "cote_n": 2.95,
      "cote_2": 2.45,
      "cyborg_pct_1": 38.0,
      "cyborg_pct_n": 29.0,
      "cyborg_pct_2": 32.0,
      "cyborg_pct_u": 50.0,
      "cyborg_pct_o": 50.0,
      "cyborg_prono": null,
      "cyborg_prono_uo": null,
      "cyborg_fav": null,
      "cyborg_fav_uo": null,
      "bettor_pct_1": 36.6,
      "bettor_pct_n": 40.7,
      "bettor_pct_2": 22.7
    }
  ],
  "ranks": [
    {
      "rank": 7,
      "nb_winners": 335,
      "payout_eur": 214.0
    },
    {
      "rank": 6,
      "nb_winners": 4713,
      "payout_eur": 18.6
    }
  ],
  "stats": {
    "nb_1": 3,
    "nb_n": 3,
    "nb_2": 1,
    "cons_1": 2,
    "cons_n": 3,
    "cons_2": 1,
    "diagonales": 0,
    "symetries": 0,
    "alternances": 3,
    "paires": 5,
    "tierces": 5,
    "quartes": 4
  }
}