{
  "record_id": "2025-grille-67",
  "grid_type": "grid-12",
  "season": "2024-2025",
  "date": "24/06/2025",
  "date_full": "Mardi 24 Juin 2025 à 20h55",
  "competition": "Autre",
  "pactole_eur": null,
  "enjeux_eur": 3.3,
  "rang1_eur": 332.7,
  "rang2_eur": 22.5,
  "nb_entries": 856,
  "total_combinations": 61632,
  "matches": [
    {
      "num": 1,
      "time": "21h00",
      "home": "Benfica",
      "away": "Bayern Munich",
      "result": "1",
      "score": "1-0",
      "cote_1": 3.65,
      "cote_n": 3.45,
      "cote_2": 2.1,
      "cyborg_pct_1": 43.0,
      "cyborg_pct_n": 27.0,
      "cyborg_pct_2": 30.0,
      "cyborg_pct_u": 50.0,
      "cyborg_pct_o": 50.0,
      "cyborg_prono": null,
      "cyborg_prono_uo": null,
      "cyborg_fav": null,
      "cyborg_fav_uo": null,
      "bettor_pct_1": 17.1,
      "bettor_pct_n": 35.1,
      "bettor_pct_2": 47.8
    },
    {
      "num": 2,
      "time": "21h00",
      "home": "Auckland City",
      "away": "Boca Juniors",
      "result": "N",
      "score": "1-1",
      "cote_1": 69.0,
      "cote_n": 16.0,
      "cote_2": 1.01,
      "cyborg_pct_1": 43.0,
      "cyborg_pct_n": 28.0,
      "cyborg_pct_2": 29.0,
      "cyborg_pct_u": 50.0,
      "cyborg_pct_o": 50.0,
      "cyborg_prono": null,
      "cyborg_prono_uo": null,
      "cyborg_fav": null,
      "cyborg_fav_uo": null,
      "bettor_pct_1": 5.78,
      "bettor_pct_n": 7.14,
      "bettor_pct_2": 87.1
    },
    {
      "num": 3,
      "time": "03h00",
      "home": "ES Tunis",
      "away": "Chelsea",
      "result": "2",
      "score": "0-3",
      "cote_1": 9.6,
      "cote_n": 5.1,
      "cote_2": 1.3,
      "cyborg_pct_1": 43.0,
      "cyborg_pct_n": 28.0,
      "cyborg_pct_2": 29.0,
      "cyborg_pct_u": 50.0,
      "cyborg_pct_o": 50.0,
      "cyborg_prono": null,
      "cyborg_prono_uo": null,
      "cyborg_fav": null,
      "cyborg_fav_uo": null,
      "bettor_pct_1": 10.0,
      "bettor_pct_n": 16.5,
      "bettor_pct_2": 73.5
    },
    {
      "num": 4,
      "time": "03h00",
      "home": "Los Angeles FC",
      "away": "Flamengo",
      "result": "N",
      "score": "1-1",
      "cote_1": 4.55,
      "cote_n": 3.6,
      "cote_2": 1.75,
      "cyborg_pct_1": 33.0,
      "cyborg_pct_n": 31.0,
      "cyborg_pct_2": 36.0,
      "cyborg_pct_u": 50.0,
      "cyborg_pct_o": 50.0,
      "cyborg_prono": null,
      "cyborg_prono_uo": null,
      "cyborg_fav": null,
      "cyborg_fav_uo": null,
      "bettor_pct_1": 16.8,
      "bettor_pct_n": 25.1,
      "bettor_pct_2": 58.1
    },
    {
      "num": 5,
      "time": "12h00",
      "home": "KawasakiFront.",
      "away": "Albirex",
      "result": "1",
      "score": "3-1",
      "cote_1": 1.65,
      "cote_n": 3.55,
      "cote_2": 4.15,
      "cyborg_pct_1": 61.0,
      "cyborg_pct_n": 23.0,
      "cyborg_pct_2": 16.0,
      "cyborg_pct_u": 47.0,
      "cyborg_pct_o": 53.0,
      "cyborg_prono": "1",
      "cyborg_prono_uo": null,
      "cyborg_fav": "1",
      "cyborg_fav_uo": null,
      "bettor_pct_1": 71.0,
      "bettor_pct_n": 18.4,
      "bettor_pct_2": 10.6
    },
    {
      "num": 6,
      "time": "12h30",
      "home": "Yokohama F.Mar",
      "away": "FC Tokyo",
      "result": "2",
      "score": "0-3",
      "cote_1": 1.95,
      "cote_n": 3.5,
      "cote_2": 3.0,
      "cyborg_pct_1": 30.0,
      "cyborg_pct_n": 32.0,
      "cyborg_pct_2": 38.0,
      "cyborg_pct_u": 62.0,
      "cyborg_pct_o": 38.0,
      "cyborg_prono": null,
      "cyborg_prono_uo": "U",
      "cyborg_fav": null,
      "cyborg_fav_uo": "U",
      "bettor_pct_1": 38.1,
      "bettor_pct_n": 29.9,
      "bettor_pct_2": 32.0
    },
    {
      "num": 7,
      "time": "13h00",
      "home": "Shanghai Shen.",
      "away": "Tianjin Tigers",
      "result": "1",
      "score": "3-0",
      "cote_1": 1.21,
      "cote_n": 5.5,
      "cote_2": 8.5,
      "cyborg_pct_1": 63.0,
      "cyborg_pct_n": 20.0,
      "cyborg_pct_2": 17.0,
      "cyborg_pct_u": 28.0,
      "cyborg_pct_o": 72.0,
      "cyborg_prono": "1",
      "cyborg_prono_uo": "O",
      "cyborg_fav": "1",
      "cyborg_fav_uo": "O",
      "bettor_pct_1": 71.1,
      "bettor_pct_n": 18.3,
      "bettor_pct_2": 10.6
    },
    {
      "num": 8,
      "time": "13h00",
      "home": "Qingdao Hainiu",
      "away": "Zhejiang FC",
      "result": "2",
      "score": "0-3",
      "cote_1": 3.0,
      "cote_n": 3.25,
      "cote_2": 2.05,
      "cyborg_pct_1": 37.0,
      "cyborg_pct_n": 38.0,
      "cyborg_pct_2": 26.0,
      "cyborg_pct_u": 65.0,
      "cyborg_pct_o": 35.0,
      "cyborg_prono": "1N",
      "cyborg_prono_uo": "U",
      "cyborg_fav": "1",
      "cyborg_fav_uo": "U",
      "bettor_pct_1": 36.5,
      "bettor_pct_n": 32.7,
      "bettor_pct_2": 30.8
    },
    {
      "num": 9,
      "time": "14h00",
      "home": "Chengdu Rong.",
      "away": "Shenzhen Peng",
      "result": "1",
      "score": "5-0",
      "cote_1": 1.17,
      "cote_n": 5.6,
      "cote_2": 10.0,
      "cyborg_pct_1": 71.0,
      "cyborg_pct_n": 18.0,
      "cyborg_pct_2": 11.0,
      "cyborg_pct_u": 54.0,
      "cyborg_pct_o": 46.0,
      "cyborg_prono": "1",
      "cyborg_prono_uo": null,
      "cyborg_fav": "1",
      "cyborg_fav_uo": null,
      "bettor_pct_1": 56.9,
      "bettor_pct_n": 20.6,
      "bettor_pct_2": 22.5
    },
    {
      "num": 10,
      "time": "13h35",
      "home": "Shandong",
      "away": "Wuhan Th.Towns",
      "result": "1",
      "score": "3-1",
      "cote_1": 1.56,
      "cote_n": 4.05,
      "cote_2": 4.15,
      "cyborg_pct_1": 45.0,
      "cyborg_pct_n": 23.0,
      "cyborg_pct_2": 32.0,
      "cyborg_pct_u": 33.0,
      "cyborg_pct_o": 67.0,
      "cyborg_prono": null,
      "cyborg_prono_uo": "O",
      "cyborg_fav": null,
      "cyborg_fav_uo": "O",
      "bettor_pct_1": 56.5,
      "bettor_pct_n": 25.3,
      "bettor_pct_2": 18.2
    },
    {
      "num": 11,
      "time": "13h35",
      "home": "Meizhou Hakka",
      "away": "Beijing Guoan",
      "result": "2",
      "score": "0-4",
      "cote_1": 4.9,
      "cote_n": 4.35,
      "cote_2": 1.44,
      "cyborg_pct_1": 8.0,
      "cyborg_pct_n": 25.0,
      "cyborg_pct_2": 68.0,
      "cyborg_pct_u": 20.0,
      "cyborg_pct_o": 80.0,
      "cyborg_prono": "2",
      "cyborg_prono_uo": "O",
      "cyborg_fav": "2",
      "cyborg_fav_uo": "O",
      "bettor_pct_1": 26.6,
      "bettor_pct_n": 21.0,
      "bettor_pct_2": 52.4
    },
    {
      "num": 12,
      "time": "18h00",
      "home": "Angleterre(21)",
      "away": "Pays-Bas(21)",
      "result": "1",
      "score": "2-1",
      "cote_1": 2.05,
      "cote_n": 3.6,
      "cote_2": 3.25,
      "cyborg_pct_1": 34.0,
      "cyborg_pct_n": 28.0,
      "cyborg_pct_2": 38.0,
      "cyborg_pct_u": 50.0,
      "cyborg_pct_o": 50.0,
      "cyborg_prono": null,
      "cyborg_prono_uo": null,
      "cyborg_fav": null,
      "cyborg_fav_uo": null,
      "bettor_pct_1": 45.3,
      "bettor_pct_n": 30.2,
      "bettor_pct_2": 24.5
    }
  ],
  "ranks": [
    {
      "rank": 12,
      "nb_winners": 1,
      "payout_eur": 41261.0
    },
    {
      "rank": 11,
      "nb_winners": 62,
      "payout_eur": 332.7
    },
    {
      "rank": 10,
      "nb_winners": 915,
      "payout_eur": 22.5
    },
    {
      "rank": 9,
      "nb_winners": 6088,
      "payout_eur": 3.3
    }
  ],
  "stats": {
    "nb_1": 6,
    "nb_n": 2,
    "nb_2": 4,
    "cons_1": 2,
    "cons_n": 1,
    "cons_2": 1,
    "diagonales": 2,
    "symetries": 1,
    "alternances": 10,
    "paires": 7,
    "tierces": 8,
    "quartes": 9
  }
}