{
  "record_id": "2023-grille-61",
  "grid_type": "grid-8",
  "season": "2022-2023",
  "date": "20/06/2023",
  "date_full": "Mardi 20 Juin 2023 à 20h40",
  "competition": "International",
  "pactole_eur": 150000.0,
  "enjeux_eur": 275036.0,
  "rang1_eur": 2000.0,
  "rang2_eur": 62.3,
  "nb_entries": 1222,
  "total_combinations": 19552,
  "matches": [
    {
      "num": 1,
      "time": "20h45",
      "home": "Islande",
      "away": "Portugal",
      "result": "2",
      "score": "0-1",
      "cote_1": 9.0,
      "cote_n": 5.7,
      "cote_2": 1.29,
      "cyborg_pct_1": 24.0,
      "cyborg_pct_n": 21.0,
      "cyborg_pct_2": 55.0,
      "cyborg_pct_u": 50.0,
      "cyborg_pct_o": 50.0,
      "cyborg_prono": "2",
      "cyborg_prono_uo": null,
      "cyborg_fav": "2",
      "cyborg_fav_uo": null,
      "bettor_pct_1": 5.26,
      "bettor_pct_n": 23.0,
      "bettor_pct_2": 71.7
    },
    {
      "num": 2,
      "time": "20h45",
      "home": "Estonie",
      "away": "Belgique",
      "result": "2",
      "score": "0-3",
      "cote_1": 11.5,
      "cote_n": 5.9,
      "cote_2": 1.31,
      "cyborg_pct_1": 33.0,
      "cyborg_pct_n": 27.0,
      "cyborg_pct_2": 40.0,
      "cyborg_pct_u": 50.0,
      "cyborg_pct_o": 50.0,
      "cyborg_prono": null,
      "cyborg_prono_uo": null,
      "cyborg_fav": null,
      "cyborg_fav_uo": null,
      "bettor_pct_1": 3.7,
      "bettor_pct_n": 12.8,
      "bettor_pct_2": 83.5
    },
    {
      "num": 3,
      "time": "20h45",
      "home": "Bulgarie",
      "away": "Serbie",
      "result": "N",
      "score": "1-1",
      "cote_1": 7.6,
      "cote_n": 4.6,
      "cote_2": 1.43,
      "cyborg_pct_1": 29.0,
      "cyborg_pct_n": 26.0,
      "cyborg_pct_2": 45.0,
      "cyborg_pct_u": 50.0,
      "cyborg_pct_o": 50.0,
      "cyborg_prono": null,
      "cyborg_prono_uo": null,
      "cyborg_fav": null,
      "cyborg_fav_uo": null,
      "bettor_pct_1": 21.1,
      "bettor_pct_n": 34.6,
      "bettor_pct_2": 44.3
    },
    {
      "num": 4,
      "time": "20h45",
      "home": "Ecosse",
      "away": "Géorgie",
      "result": "1",
      "score": "2-0",
      "cote_1": 1.56,
      "cote_n": 4.0,
      "cote_2": 6.4,
      "cyborg_pct_1": 43.0,
      "cyborg_pct_n": 23.0,
      "cyborg_pct_2": 33.0,
      "cyborg_pct_u": 50.0,
      "cyborg_pct_o": 50.0,
      "cyborg_prono": null,
      "cyborg_prono_uo": null,
      "cyborg_fav": null,
      "cyborg_fav_uo": null,
      "bettor_pct_1": 61.9,
      "bettor_pct_n": 32.0,
      "bettor_pct_2": 6.1
    },
    {
      "num": 5,
      "time": "20h45",
      "home": "Bosnie Herzég.",
      "away": "Luxembourg",
      "result": "2",
      "score": "0-2",
      "cote_1": 1.52,
      "cote_n": 4.15,
      "cote_2": 6.75,
      "cyborg_pct_1": 41.0,
      "cyborg_pct_n": 32.0,
      "cyborg_pct_2": 28.0,
      "cyborg_pct_u": 50.0,
      "cyborg_pct_o": 50.0,
      "cyborg_prono": null,
      "cyborg_prono_uo": null,
      "cyborg_fav": null,
      "cyborg_fav_uo": null,
      "bettor_pct_1": 63.8,
      "bettor_pct_n": 28.0,
      "bettor_pct_2": 8.26
    },
    {
      "num": 6,
      "time": "20h45",
      "home": "Norvège",
      "away": "Chypre",
      "result": "1",
      "score": "3-1",
      "cote_1": 1.12,
      "cote_n": 9.0,
      "cote_2": 24.0,
      "cyborg_pct_1": 39.0,
      "cyborg_pct_n": 26.0,
      "cyborg_pct_2": 35.0,
      "cyborg_pct_u": 50.0,
      "cyborg_pct_o": 50.0,
      "cyborg_prono": null,
      "cyborg_prono_uo": null,
      "cyborg_fav": null,
      "cyborg_fav_uo": null,
      "bettor_pct_1": 82.7,
      "bettor_pct_n": 14.0,
      "bettor_pct_2": 3.31
    },
    {
      "num": 7,
      "time": "20h45",
      "home": "Moldavie",
      "away": "Pologne",
      "result": "1",
      "score": "3-2",
      "cote_1": 9.0,
      "cote_n": 4.65,
      "cote_2": 1.44,
      "cyborg_pct_1": 36.0,
      "cyborg_pct_n": 37.0,
      "cyborg_pct_2": 27.0,
      "cyborg_pct_u": 50.0,
      "cyborg_pct_o": 50.0,
      "cyborg_prono": "1N",
      "cyborg_prono_uo": null,
      "cyborg_fav": "1",
      "cyborg_fav_uo": null,
      "bettor_pct_1": 6.15,
      "bettor_pct_n": 29.7,
      "bettor_pct_2": 64.1
    },
    {
      "num": 8,
      "time": "20h45",
      "home": "Autriche",
      "away": "Suède",
      "result": "1",
      "score": "2-0",
      "cote_1": 2.05,
      "cote_n": 3.5,
      "cote_2": 3.6,
      "cyborg_pct_1": 60.0,
      "cyborg_pct_n": 19.0,
      "cyborg_pct_2": 21.0,
      "cyborg_pct_u": 50.0,
      "cyborg_pct_o": 50.0,
      "cyborg_prono": "1",
      "cyborg_prono_uo": null,
      "cyborg_fav": "1",
      "cyborg_fav_uo": null,
      "bettor_pct_1": 41.5,
      "bettor_pct_n": 34.8,
      "bettor_pct_2": 23.8
    }
  ],
  "ranks": [
    {
      "rank": 8,
      "nb_winners": 75,
      "payout_eur": 2000.0
    },
    {
      "rank": 7,
      "nb_winners": 2007,
      "payout_eur": 62.3
    }
  ],
  "stats": {
    "nb_1": 4,
    "nb_n": 1,
    "nb_2": 3,
    "cons_1": 3,
    "cons_n": 1,
    "cons_2": 2,
    "diagonales": 1,
    "symetries": 0,
    "alternances": 4,
    "paires": 6,
    "tierces": 6,
    "quartes": 5
  }
}