{
  "record_id": "2022-grille-254",
  "grid_type": "grid-7",
  "season": "2022-2023",
  "date": "15/12/2022",
  "date_full": "Jeudi 15 Décembre 2022 à 18h40",
  "competition": "Autre",
  "pactole_eur": null,
  "enjeux_eur": 111826.0,
  "rang1_eur": 34.0,
  "rang2_eur": 5.6,
  "nb_entries": 1291,
  "total_combinations": 10328,
  "matches": [
    {
      "num": 1,
      "time": "21h00",
      "home": "Rangers",
      "away": "Hibernian",
      "result": "1",
      "score": "3-2",
      "cote_1": 1.27,
      "cote_n": 5.35,
      "cote_2": 9.0,
      "cyborg_pct_1": 88.0,
      "cyborg_pct_n": 7.0,
      "cyborg_pct_2": 5.0,
      "cyborg_pct_u": 36.0,
      "cyborg_pct_o": 64.0,
      "cyborg_prono": "1",
      "cyborg_prono_uo": "O",
      "cyborg_fav": "1",
      "cyborg_fav_uo": "O",
      "bettor_pct_1": 86.7,
      "bettor_pct_n": 8.46,
      "bettor_pct_2": 4.88
    },
    {
      "num": 2,
      "time": null,
      "home": "FCSB",
      "away": "Cfr Cluj",
      "result": "2",
      "score": null,
      "cote_1": null,
      "cote_n": null,
      "cote_2": null,
      "cyborg_pct_1": null,
      "cyborg_pct_n": null,
      "cyborg_pct_2": null,
      "cyborg_pct_u": null,
      "cyborg_pct_o": null,
      "cyborg_prono": null,
      "cyborg_prono_uo": null,
      "cyborg_fav": null,
      "cyborg_fav_uo": null,
      "bettor_pct_1": null,
      "bettor_pct_n": null,
      "bettor_pct_2": null
    },
    {
      "num": 3,
      "time": null,
      "home": "Arsenal",
      "away": "Lyon",
      "result": "2",
      "score": null,
      "cote_1": null,
      "cote_n": null,
      "cote_2": null,
      "cyborg_pct_1": null,
      "cyborg_pct_n": null,
      "cyborg_pct_2": null,
      "cyborg_pct_u": null,
      "cyborg_pct_o": null,
      "cyborg_prono": null,
      "cyborg_prono_uo": null,
      "cyborg_fav": null,
      "cyborg_fav_uo": null,
      "bettor_pct_1": null,
      "bettor_pct_n": null,
      "bettor_pct_2": null
    },
    {
      "num": 4,
      "time": null,
      "home": "SL Benfica",
      "away": "FC Barcelone",
      "result": "2",
      "score": null,
      "cote_1": null,
      "cote_n": null,
      "cote_2": null,
      "cyborg_pct_1": null,
      "cyborg_pct_n": null,
      "cyborg_pct_2": null,
      "cyborg_pct_u": null,
      "cyborg_pct_o": null,
      "cyborg_prono": null,
      "cyborg_prono_uo": null,
      "cyborg_fav": null,
      "cyborg_fav_uo": null,
      "bettor_pct_1": null,
      "bettor_pct_n": null,
      "bettor_pct_2": null
    },
    {
      "num": 5,
      "time": null,
      "home": "FC Rosengard",
      "away": "Bayern Munich",
      "result": "2",
      "score": null,
      "cote_1": null,
      "cote_n": null,
      "cote_2": null,
      "cyborg_pct_1": null,
      "cyborg_pct_n": null,
      "cyborg_pct_2": null,
      "cyborg_pct_u": null,
      "cyborg_pct_o": null,
      "cyborg_prono": null,
      "cyborg_prono_uo": null,
      "cyborg_fav": null,
      "cyborg_fav_uo": null,
      "bettor_pct_1": null,
      "bettor_pct_n": null,
      "bettor_pct_2": null
    },
    {
      "num": 6,
      "time": null,
      "home": "Viseu",
      "away": "CD Tondela",
      "result": "1",
      "score": null,
      "cote_1": null,
      "cote_n": null,
      "cote_2": null,
      "cyborg_pct_1": null,
      "cyborg_pct_n": null,
      "cyborg_pct_2": null,
      "cyborg_pct_u": null,
      "cyborg_pct_o": null,
      "cyborg_prono": null,
      "cyborg_prono_uo": null,
      "cyborg_fav": null,
      "cyborg_fav_uo": null,
      "bettor_pct_1": null,
      "bettor_pct_n": null,
      "bettor_pct_2": null
    },
    {
      "num": 7,
      "time": null,
      "home": "Estoril Praia",
      "away": "Famalicao",
      "result": "2",
      "score": null,
      "cote_1": null,
      "cote_n": null,
      "cote_2": null,
      "cyborg_pct_1": null,
      "cyborg_pct_n": null,
      "cyborg_pct_2": null,
      "cyborg_pct_u": null,
      "cyborg_pct_o": null,
      "cyborg_prono": null,
      "cyborg_prono_uo": null,
      "cyborg_fav": null,
      "cyborg_fav_uo": null,
      "bettor_pct_1": null,
      "bettor_pct_n": null,
      "bettor_pct_2": null
    }
  ],
  "ranks": [
    {
      "rank": 7,
      "nb_winners": 1484,
      "payout_eur": 34.0
    },
    {
      "rank": 6,
      "nb_winners": 10959,
      "payout_eur": 5.6
    }
  ],
  "stats": {
    "nb_1": 2,
    "nb_n": 0,
    "nb_2": 5,
    "cons_1": 1,
    "cons_n": 0,
    "cons_2": 4,
    "diagonales": 0,
    "symetries": 1,
    "alternances": 3,
    "paires": 3,
    "tierces": 4,
    "quartes": 4
  }
}